report_compiler/__init__.py
report_compiler/_version.py
report_compiler/cli.py
report_compiler/interactive_menu.py
report_compiler/core/__init__.py
report_compiler/core/compiler.py
report_compiler/core/config.py
report_compiler/document/__init__.py
report_compiler/document/docx_processor.py
report_compiler/document/libreoffice_converter.py
report_compiler/document/placeholder_parser.py
report_compiler/document/word_converter.py
report_compiler/pdf/__init__.py
report_compiler/pdf/content_analyzer.py
report_compiler/pdf/marker_remover.py
report_compiler/pdf/merge_processor.py
report_compiler/pdf/overlay_processor.py
report_compiler/utils/__init__.py
report_compiler/utils/conversions.py
report_compiler/utils/docx_emf_patch.py
report_compiler/utils/file_manager.py
report_compiler/utils/logging_config.py
report_compiler/utils/page_selector.py
report_compiler/utils/pdf_to_svg.py
report_compiler/utils/validators.py
report_compiler/utils/word_integration_manager.py
report_compiler-0.1.15.dist-info/METADATA
report_compiler-0.1.15.dist-info/WHEEL
report_compiler-0.1.15.dist-info/entry_points.txt
report_compiler-0.1.15.dist-info/top_level.txt
report_compiler-0.1.15.dist-info/RECORD
