Metadata-Version: 2.4
Name: report-compiler
Version: 0.1.15
Summary: A tool for compiling reports from various sources.
Author-email: YOUR NAME <your@email.com>
Classifier: Programming Language :: Python :: 3
Classifier: License :: OSI Approved :: MIT License
Classifier: Operating System :: OS Independent
Requires-Python: >=3.9
Requires-Dist: comtypes>=1.2.1
Requires-Dist: Pillow>=10.2.0
Requires-Dist: python-docx>=1.2.0
Requires-Dist: PyMuPDF>=1.26.3
Requires-Dist: typer>=0.9.0
Requires-Dist: pywin32; sys_platform == "win32"
Requires-Dist: questionary>=2.0.1
